{
  "@context": "https://schema.org",
  "@type": "Recipe",
  "name": "One-Pan Garlic Butter Shrimp Pasta",
  "description": "A quick and flavorful garlic butter shrimp pasta that comes together in about twenty minutes.",
  "recipeCuisine": "Italian-American",
  "recipeCategory": "main course",
  "keywords": "shrimp, pasta, garlic butter, one-pan, quick meal",
  "recipeYield": "4 servings",
  "cookTime": "PT20M",
  "totalTime": "PT20M",
  "recipeIngredient": [
    "12 oz linguine",
    "1 lb large shrimp",
    "4 tbsp butter",
    "5 clove garlic (minced)",
    "0.5 cup dry white wine",
    "1 lemon",
    "0.5 cup parmesan",
    "0.25 cup parsley (fresh)",
    "0.5 tsp red pepper flakes",
    "salt",
    "pepper"
  ],
  "recipeInstructions": [
    {
      "@type": "HowToStep",
      "position": 1,
      "text": "Bring a large pot of salted water to a boil and cook the linguine until al dente.",
      "name": "Step 1"
    },
    {
      "@type": "HowToStep",
      "position": 2,
      "text": "Pat the shrimp dry and season them with salt and pepper.",
      "name": "Step 2"
    },
    {
      "@type": "HowToStep",
      "position": 3,
      "text": "Melt butter in a large skillet over medium heat, then add the garlic and cook until fragrant.",
      "name": "Step 3"
    },
    {
      "@type": "HowToStep",
      "position": 4,
      "text": "Add the shrimp and cook for about two minutes per side until they turn pink.",
      "name": "Step 4"
    },
    {
      "@type": "HowToStep",
      "position": 5,
      "text": "Pour in the white wine and lemon juice, and let it reduce for a minute.",
      "name": "Step 5"
    },
    {
      "@type": "HowToStep",
      "position": 6,
      "text": "Add the cooked pasta straight into the skillet with a splash of pasta water.",
      "name": "Step 6"
    },
    {
      "@type": "HowToStep",
      "position": 7,
      "text": "Finish with parmesan, fresh parsley, and a pinch of red pepper flakes. Serve immediately.",
      "name": "Step 7"
    }
  ],
  "tool": [
    "large pot",
    "large stainless skillet",
    "paper towels"
  ],
  "author": {
    "@type": "Person",
    "name": "Demo Kitchen"
  },
  "isBasedOn": "https://youtube.com/shorts/demo",
  "nutrition": {
    "@type": "NutritionInformation",
    "calories": "580 calories",
    "proteinContent": "32.0 g",
    "carbohydrateContent": "55.0 g",
    "fatContent": "24.0 g"
  }
}